irr_uncertainty/__init__.py
irr_uncertainty/config.py
irr_uncertainty/pv_uncertainty_2024_article.py
irr_uncertainty/utils.py
irr_uncertainty/data/__init__.py
irr_uncertainty/data/irr_data.py
irr_uncertainty/data/solar_data.py
irr_uncertainty/local_data/ghi_dhi_bhi_pvgis_2015.csv
irr_uncertainty/local_data/readme.txt
irr_uncertainty/local_data/secret.ini
irr_uncertainty/local_data/bsrn_data/readme.txt
irr_uncertainty/local_data/cams_data/readme.txt
irr_uncertainty/local_data/irr_data/kd_dist_v2_cams_pvlib_None.pkl
irr_uncertainty/local_data/irr_data/readme.txt
irr_uncertainty/local_data/irr_limits/readme.txt
irr_uncertainty/local_data/pv_live/readme.txt
irr_uncertainty/local_data/solar_pos/readme.txt
irr_uncertainty/models/__init__.py
irr_uncertainty/models/irr_limits.py
irr_uncertainty/models/optic_model.py
irr_uncertainty/models/uncertainty_config.py
irr_uncertainty/models/uncertainty_model.py
irr_uncertainty-1.4.dist-info/licenses/LICENSE
irr_uncertainty-1.4.dist-info/METADATA
irr_uncertainty-1.4.dist-info/WHEEL
irr_uncertainty-1.4.dist-info/top_level.txt
irr_uncertainty-1.4.dist-info/RECORD
