Metadata-Version: 2.4
Name: irr_uncertainty
Version: 1.4
Summary: Irradiance uncertainty package
Home-page: https://github.com/AlexandreHugoMathieu/irr_uncertainty
Author: Alexandre MATHIEU
Author-email: mathalex@gmail.com
Requires-Python: >=3.9
License-File: LICENSE
Requires-Dist: scikit-learn
Requires-Dist: global_land_mask
Requires-Dist: fiona~=1.9.6
Requires-Dist: geopandas~=0.13.2
Requires-Dist: matplotlib~=3.4.1
Requires-Dist: notebook~=7.3.2
Requires-Dist: openpyxl~=3.1.2
Requires-Dist: seaborn>=0.13.2
Requires-Dist: tqdm>=4.64.1
Requires-Dist: pvlib==0.10.2
Requires-Dist: PyAstronomy~=0.22.0
Requires-Dist: numpy==1.21.0
Requires-Dist: pandas~=1.4.1
Dynamic: author
Dynamic: author-email
Dynamic: description
Dynamic: description-content-type
Dynamic: home-page
Dynamic: license-file
Dynamic: requires-dist
Dynamic: requires-python
Dynamic: summary
